openakita/__init__.py
openakita/__main__.py
openakita/config.py
openakita/main.py
openakita/channels/__init__.py
openakita/channels/base.py
openakita/channels/gateway.py
openakita/channels/types.py
openakita/channels/adapters/__init__.py
openakita/channels/adapters/dingtalk.py
openakita/channels/adapters/feishu.py
openakita/channels/adapters/qq.py
openakita/channels/adapters/telegram.py
openakita/channels/adapters/wework.py
openakita/channels/media/__init__.py
openakita/channels/media/handler.py
openakita/channels/media/storage.py
openakita/core/__init__.py
openakita/core/agent.py
openakita/core/brain.py
openakita/core/identity.py
openakita/core/memory.py
openakita/core/ralph.py
openakita/core/user_profile.py
openakita/evolution/__init__.py
openakita/evolution/analyzer.py
openakita/evolution/generator.py
openakita/evolution/installer.py
openakita/evolution/self_check.py
openakita/memory/__init__.py
openakita/memory/consolidator.py
openakita/memory/daily_consolidator.py
openakita/memory/extractor.py
openakita/memory/manager.py
openakita/memory/types.py
openakita/memory/vector_store.py
openakita/orchestration/__init__.py
openakita/orchestration/bus.py
openakita/orchestration/master.py
openakita/orchestration/messages.py
openakita/orchestration/monitor.py
openakita/orchestration/registry.py
openakita/orchestration/worker.py
openakita/scheduler/__init__.py
openakita/scheduler/executor.py
openakita/scheduler/scheduler.py
openakita/scheduler/task.py
openakita/scheduler/triggers.py
openakita/sessions/__init__.py
openakita/sessions/manager.py
openakita/sessions/session.py
openakita/sessions/user.py
openakita/setup/__init__.py
openakita/setup/wizard.py
openakita/skills/__init__.py
openakita/skills/catalog.py
openakita/skills/loader.py
openakita/skills/parser.py
openakita/skills/registry.py
openakita/storage/__init__.py
openakita/storage/database.py
openakita/storage/models.py
openakita/testing/__init__.py
openakita/testing/fixer.py
openakita/testing/judge.py
openakita-1.0.3.dist-info/METADATA
openakita-1.0.3.dist-info/WHEEL
openakita-1.0.3.dist-info/entry_points.txt
openakita-1.0.3.dist-info/licenses/LICENSE
openakita-1.0.3.dist-info/RECORD
