Metadata-Version: 2.4
Name: openakita
Version: 1.0.3
Summary: 全能自进化AI Agent - 基于Ralph Wiggum模式，永不放弃
Author-email: OpenAkita <zacon365@gmail.com>
License: MIT
License-File: LICENSE
Keywords: agent,ai,autonomous,claude,self-evolving
Classifier: Development Status :: 3 - Alpha
Classifier: Intended Audience :: Developers
Classifier: License :: OSI Approved :: MIT License
Classifier: Programming Language :: Python :: 3.11
Classifier: Programming Language :: Python :: 3.12
Requires-Python: >=3.11
Requires-Dist: aiofiles>=24.1.0
Requires-Dist: aiosqlite>=0.20.0
Requires-Dist: anthropic>=0.40.0
Requires-Dist: chromadb>=0.4.0
Requires-Dist: gitpython>=3.1.40
Requires-Dist: httpx>=0.27.0
Requires-Dist: mcp>=1.0.0
Requires-Dist: openai>=1.0.0
Requires-Dist: playwright>=1.40.0
Requires-Dist: prompt-toolkit>=3.0.43
Requires-Dist: pydantic-settings>=2.1.0
Requires-Dist: pydantic>=2.5.0
Requires-Dist: python-dotenv>=1.0.0
Requires-Dist: python-telegram-bot>=21.0
Requires-Dist: pyyaml>=6.0.1
Requires-Dist: pyzmq>=25.0.0
Requires-Dist: rich>=13.7.0
Requires-Dist: sentence-transformers>=2.2.0
Requires-Dist: tenacity>=8.2.3
Requires-Dist: typer>=0.12.0
Provides-Extra: dev
Requires-Dist: mypy>=1.8.0; extra == 'dev'
Requires-Dist: pytest-asyncio>=0.23.0; extra == 'dev'
Requires-Dist: pytest-cov>=4.1.0; extra == 'dev'
Requires-Dist: pytest>=8.0.0; extra == 'dev'
Requires-Dist: ruff>=0.1.9; extra == 'dev'
